resc_backend/__init__.py
resc_backend/common.py
resc_backend/constants.py
resc_backend/bin/__init__.py
resc_backend/bin/rabbitmq_bootup.py
resc_backend/db/__init__.py
resc_backend/db/connection.py
resc_backend/db/engine_azure.py
resc_backend/db/model/__init__.py
resc_backend/db/model/audit.py
resc_backend/db/model/finding.py
resc_backend/db/model/repository.py
resc_backend/db/model/rule.py
resc_backend/db/model/rule_allow_list.py
resc_backend/db/model/rule_pack.py
resc_backend/db/model/rule_tag.py
resc_backend/db/model/scan.py
resc_backend/db/model/scan_finding.py
resc_backend/db/model/tag.py
resc_backend/db/model/vcs_instance.py
resc_backend/helpers/__init__.py
resc_backend/helpers/dict_remapper.py
resc_backend/helpers/environment_wrapper.py
resc_backend/helpers/rabbitmq/__init__.py
resc_backend/helpers/rabbitmq/configuration.py
resc_backend/helpers/rabbitmq/rabbitmq_initialization.py
resc_backend/resc_web_service/__init__.py
resc_backend/resc_web_service/api.py
resc_backend/resc_web_service/cache_manager.py
resc_backend/resc_web_service/configuration.py
resc_backend/resc_web_service/dependencies.py
resc_backend/resc_web_service/filters.py
resc_backend/resc_web_service/local.py
resc_backend/resc_web_service/crud/__init__.py
resc_backend/resc_web_service/crud/audit.py
resc_backend/resc_web_service/crud/detailed_finding.py
resc_backend/resc_web_service/crud/finding.py
resc_backend/resc_web_service/crud/repository.py
resc_backend/resc_web_service/crud/rule.py
resc_backend/resc_web_service/crud/rule_pack.py
resc_backend/resc_web_service/crud/rule_tag.py
resc_backend/resc_web_service/crud/scan.py
resc_backend/resc_web_service/crud/scan_finding.py
resc_backend/resc_web_service/crud/vcs_instance.py
resc_backend/resc_web_service/endpoints/__init__.py
resc_backend/resc_web_service/endpoints/common.py
resc_backend/resc_web_service/endpoints/detailed_findings.py
resc_backend/resc_web_service/endpoints/findings.py
resc_backend/resc_web_service/endpoints/health.py
resc_backend-4.0.0.dist-info/LICENSE.md
resc_backend-4.0.0.dist-info/METADATA
resc_backend-4.0.0.dist-info/WHEEL
resc_backend-4.0.0.dist-info/entry_points.txt
resc_backend-4.0.0.dist-info/top_level.txt
resc_backend-4.0.0.dist-info/RECORD
