Metadata-Version: 2.1
Name: resc_backend
Version: 4.0.0
Summary: Repository Scanner - Backend
Home-page: https://github.com/ABNAMRO/repository-scanner
Download-URL: 
Author: ABN AMRO
Author-email: resc@nl.abnamro.com
Requires-Python: >=3.12
License-File: LICENSE.md
Requires-Dist: celery ==5.3.1
Requires-Dist: amqp ==5.1.1
Requires-Dist: requests ==2.31.0
Requires-Dist: sqlalchemy ==2.0.20
Requires-Dist: alembic ==1.11.2
Requires-Dist: fastapi ==0.110.2
Requires-Dist: typing ==3.7.4.3
Requires-Dist: pydantic ==1.10.15
Requires-Dist: uvicorn ==0.17.6
Requires-Dist: waitress ==2.1.2
Requires-Dist: pyjwt[crypto] ==2.8.0
Requires-Dist: cryptography ==42.0.4
Requires-Dist: tenacity ==8.2.2
Requires-Dist: tomlkit ==0.12.1
Requires-Dist: python-multipart ==0.0.7
Requires-Dist: aiofiles ==0.8.0
Requires-Dist: packaging ==23.1
Requires-Dist: fastapi-cache2 ==0.2.1
Requires-Dist: redis ==4.6.0
Requires-Dist: azure-identity ==1.15.0
Requires-Dist: setuptools ==69.5.1
